taxi_data_advanced/__init__.py
taxi_data_advanced/automate_bwc_web_site.py
taxi_data_advanced/automate_gps_tracker_web_site.py
taxi_data_advanced/browser_init.py
taxi_data_advanced/classes.py
taxi_data_advanced/constants.py
taxi_data_advanced/database_actions.py
taxi_data_advanced/gather_all_data.py
taxi_data_advanced/gather_bwc_data.py
taxi_data_advanced/gather_gps_data.py
taxi_data_advanced/initialize_database.py
taxi_data_advanced/requirements.txt
taxi_data_advanced/setup.py
taxi_data_advanced-0.0.9.dist-info/METADATA
taxi_data_advanced-0.0.9.dist-info/WHEEL
taxi_data_advanced-0.0.9.dist-info/licenses/LICENSE
taxi_data_advanced-0.0.9.dist-info/RECORD
