Metadata-Version: 2.3
Name: taxi_data_advanced
Version: 0.0.9
Summary: Export data from web portals and save to database.
Project-URL: Homepage, https://github.com/WayneBennett666/taxi-data_advanced
Project-URL: Issues, https://github.com/WayneBennett666/taxi-data_advanced/issues
Author-email: Wayne Bennett <wayne.bennett@live.com>
License-File: LICENSE
Classifier: License :: OSI Approved :: MIT License
Classifier: Operating System :: OS Independent
Classifier: Programming Language :: Python :: 3
Requires-Python: >=3.10
